pyros_support_ui/__init__.py
pyros_support_ui/agent.py
pyros_support_ui/box_blue_sf_theme.py
pyros_support_ui/components.py
pyros_support_ui/drop_down.py
pyros_support_ui/flat_theme.py
pyros_support_ui/gcc.py
pyros_support_ui/gccui.py
pyros_support_ui/graph_component.py
pyros_support_ui/number_input.py
pyros_support_ui/pygamehelper.py
pyros_support_ui/pyros_client_app.py
pyros_support_ui/text_toggle_button.py
pyros_support_ui-1.2.0.dist-info/LICENSE
pyros_support_ui-1.2.0.dist-info/METADATA
pyros_support_ui-1.2.0.dist-info/WHEEL
pyros_support_ui-1.2.0.dist-info/top_level.txt
pyros_support_ui-1.2.0.dist-info/RECORD
