Metadata-Version: 2.1
Name: pyros-support-ui
Version: 1.2.0
Summary: Support library for (pygame based) UI components
Home-page: https://github.com/Abstract-Horizon/pyros-support-ui
Author: Daniel Sendula
License: UNKNOWN
Platform: UNKNOWN
Classifier: Programming Language :: Python :: 3
Classifier: License :: OSI Approved :: Apache Software License
Classifier: Operating System :: OS Independent
Requires-Python: >=3.6
License-File: LICENSE
Requires-Dist: pygame
Requires-Dist: pyros-client
Requires-Dist: local-resources
Requires-Dist: pyros-discovery
